osinfopkg/__init__.py
osinfopkg/osinfopkg.py
osinfopkg-0.0.4.dist-info/METADATA
osinfopkg-0.0.4.dist-info/WHEEL
osinfopkg-0.0.4.dist-info/licenses/LICENSE
osinfopkg-0.0.4.dist-info/RECORD
